NaxToPy/NaxToPy.ico
NaxToPy/__init__.py
NaxToPy/user_functions.txt
NaxToPy/Core/N2PModelContent.py
NaxToPy/Core/__init__.py
NaxToPy/Core/Classes/AllClasses.py
NaxToPy/Core/Classes/N2PAbaqusInputData.py
NaxToPy/Core/Classes/N2PComponent.py
NaxToPy/Core/Classes/N2PConnector.py
NaxToPy/Core/Classes/N2PCoord.py
NaxToPy/Core/Classes/N2PElement.py
NaxToPy/Core/Classes/N2PFreeBody.py
NaxToPy/Core/Classes/N2PIncrement.py
NaxToPy/Core/Classes/N2PLoadCase.py
NaxToPy/Core/Classes/N2PMaterial.py
NaxToPy/Core/Classes/N2PNastranInputData.py
NaxToPy/Core/Classes/N2PNode.py
NaxToPy/Core/Classes/N2PProperty.py
NaxToPy/Core/Classes/N2PReport.py
NaxToPy/Core/Classes/N2PResult.py
NaxToPy/Core/Classes/N2PSection.py
NaxToPy/Core/Classes/N2PSet.py
NaxToPy/Core/Classes/ProgresBar.py
NaxToPy/Core/Classes/__init__.py
NaxToPy/Core/Classes/ABQEntities/N2PEntity.py
NaxToPy/Core/Classes/ABQEntities/N2PEntityElement.py
NaxToPy/Core/Classes/ABQEntities/N2PEntityNode.py
NaxToPy/Core/Classes/ABQEntities/N2PEntityShell.py
NaxToPy/Core/Classes/ABQEntities/__init__.py
NaxToPy/Core/Classes/ABQKeywords/N2PKeyword.py
NaxToPy/Core/Classes/ABQKeywords/N2PKeywordBEAMSECTION.py
NaxToPy/Core/Classes/ABQKeywords/N2PKeywordCOUPLING.py
NaxToPy/Core/Classes/ABQKeywords/N2PKeywordDENSITY.py
NaxToPy/Core/Classes/ABQKeywords/N2PKeywordDISTRIBUTING.py
NaxToPy/Core/Classes/ABQKeywords/N2PKeywordDISTRIBUTINGCOUPLING.py
NaxToPy/Core/Classes/ABQKeywords/N2PKeywordELASTIC.py
NaxToPy/Core/Classes/ABQKeywords/N2PKeywordELEMENT.py
NaxToPy/Core/Classes/ABQKeywords/N2PKeywordELSET.py
NaxToPy/Core/Classes/ABQKeywords/N2PKeywordENDINSTANCE.py
NaxToPy/Core/Classes/ABQKeywords/N2PKeywordENDPART.py
NaxToPy/Core/Classes/ABQKeywords/N2PKeywordINSTANCE.py
NaxToPy/Core/Classes/ABQKeywords/N2PKeywordKINEMATIC.py
NaxToPy/Core/Classes/ABQKeywords/N2PKeywordKINEMATICCOUPLING.py
NaxToPy/Core/Classes/ABQKeywords/N2PKeywordMATERIAL.py
NaxToPy/Core/Classes/ABQKeywords/N2PKeywordNODE.py
NaxToPy/Core/Classes/ABQKeywords/N2PKeywordNSET.py
naxtopy-3.2.2.dist-info/licenses/LICENSE
naxtopy-3.2.2.dist-info/METADATA
naxtopy-3.2.2.dist-info/WHEEL
naxtopy-3.2.2.dist-info/top_level.txt
naxtopy-3.2.2.dist-info/RECORD
