Metadata-Version: 2.4
Name: NaxToPy
Version: 3.2.2
Summary: Package for postprocessing FEM results in Python
Home-page: https://www.idaerosolutions.com/Home/NaxToPy
Download-URL: https://apps.microsoft.com/detail/XP9MMH0KDKGRJN?hl=en-US&gl=US
Author-email: Idaero Solutions <manuel.sanchez@idaerosolutions.com>
License: MIT
Project-URL: Documentation, https://www.idaerosolutions.com/NaxToDocumentation/NaxToPy/3.1.0/index.html
Project-URL: LinkedIn, https://www.linkedin.com/company/idaero/
Keywords: NaxTo,Postprocessing,FEM
Classifier: Intended Audience :: Science/Research
Classifier: Programming Language :: Python :: 3.9
Classifier: License :: Other/Proprietary License
Classifier: Operating System :: Microsoft :: Windows :: Windows 10
Classifier: Topic :: Scientific/Engineering
Requires-Python: >=3.9
License-File: LICENSE
Requires-Dist: pythonnet>=3.0.4
Requires-Dist: numpy>=1.26.0
Requires-Dist: setuptools>=67.8.0
Requires-Dist: h5py>=3.12.1
Dynamic: download-url
Dynamic: home-page
Dynamic: license-file
